byoc/__init__.py
byoc/app.py
byoc/cast.py
byoc/errors.py
byoc/getters.py
byoc/key.py
byoc/meta.py
byoc/model.py
byoc/pick.py
byoc/utils.py
byoc/configs/__init__.py
byoc/configs/attrs.py
byoc/configs/configs.py
byoc/configs/layers.py
byoc/configs/on_load.py
byoc/params/__init__.py
byoc/params/inherited.py
byoc/params/param.py
byoc/params/toggle.py
byoc-0.32.0.dist-info/LICENSE.txt
byoc-0.32.0.dist-info/WHEEL
byoc-0.32.0.dist-info/METADATA
byoc-0.32.0.dist-info/RECORD
