Metadata-Version: 2.1
Name: byoc
Version: 0.32.0
Summary: An object-oriented framework for command-line apps.
Author-email: Kale Kundert <kale@thekunderts.net>
Requires-Python: ~=3.7
Classifier: Programming Language :: Python :: 3.6
Requires-Dist: autoprop
Requires-Dist: appdirs
Requires-Dist: docopt~=0.6.2
Requires-Dist: funcy
Requires-Dist: mako
Requires-Dist: more_itertools
Requires-Dist: nestedtext
Requires-Dist: pyyaml
Requires-Dist: tidyexc
Requires-Dist: tomli
Requires-Dist: jmespath
Requires-Dist: sphinx ; extra == "docs"
Requires-Dist: sphinx_rtd_theme ; extra == "docs"
Requires-Dist: sphinx-inline-tabs ; extra == "docs"
Requires-Dist: sphinx-copybutton ; extra == "docs"
Requires-Dist: autoclasstoc ; extra == "docs"
Requires-Dist: pytest ; extra == "tests"
Requires-Dist: pytest-cov ; extra == "tests"
Requires-Dist: pytest-unordered ; extra == "tests"
Requires-Dist: coveralls ; extra == "tests"
Requires-Dist: parametrize_from_file ; extra == "tests"
Requires-Dist: voluptuous ; extra == "tests"
Requires-Dist: re-assert ; extra == "tests"
Requires-Dist: dataclasses ; extra == "tests"
Project-URL: Bug Tracker, https://github.com/kalekundert/byoc/issues
Project-URL: Continuous Integration, https://github.com/kalekundert/byoc/actions
Project-URL: Documentation, https://byoc.readthedocs.io/en/latest/
Project-URL: Test Coverage, https://coveralls.io/github/kalekundert/byoc
Project-URL: Version Control, https://github.com/kalekundert/byoc
Provides-Extra: docs
Provides-Extra: tests
